{
  "id": "support/support-model",
  "title": "Support model",
  "description": "Support",
  "source": "@site/docs/support/support-model.md",
  "sourceDirName": "support",
  "slug": "/support/support-model",
  "permalink": "/docs/support/support-model",
  "draft": false,
  "unlisted": false,
  "tags": [],
  "version": "current",
  "frontMatter": {
    "title": "Support model",
    "slug": "/support/support-model"
  },
  "sidebar": "docs",
  "previous": {
    "title": "Runtime overview",
    "permalink": "/docs/reference/runtime-overview"
  },
  "next": {
    "title": "EULA",
    "permalink": "/docs/legal/eula"
  }
}